MANIFEST.in
setup.cfg
setup.py
examples/minimal.vcf
examples/small_vep.vcf
examples/test_vcf.vcf
examples/test_vcf.vcf.gz
vcf_parser/__init__.py
vcf_parser/genotype.py
vcf_parser/header_parser.py
vcf_parser/log.py
vcf_parser/parser.py
vcf_parser.egg-info/PKG-INFO
vcf_parser.egg-info/SOURCES.txt
vcf_parser.egg-info/dependency_links.txt
vcf_parser.egg-info/entry_points.txt
vcf_parser.egg-info/requires.txt
vcf_parser.egg-info/top_level.txt
vcf_parser/cli/__init__.py
vcf_parser/cli/command_line.py
vcf_parser/utils/__init__.py
vcf_parser/utils/build_compounds.py
vcf_parser/utils/build_info.py
vcf_parser/utils/build_models.py
vcf_parser/utils/build_vep.py
vcf_parser/utils/check_info.py
vcf_parser/utils/format_variant.py
vcf_parser/utils/rank_scores.py
vcf_parser/utils/split_genotype.py
vcf_parser/utils/split_variants.py