Metadata-Version: 1.1
Name: vcf-parser
Version: 1.5
Summary: Parsing vcf files
Home-page: http://github.com/moonso/vcf_parser
Author: Mans Magnusson
Author-email: mans.magnusson@scilifelab.se
License: MIT License
Keywords: parser,vcf,variants
Platform: UNKNOWN
Classifier: Programming Language :: Python
Classifier: Programming Language :: Python :: 2.7
Classifier: Programming Language :: Python :: 3
Classifier: License :: OSI Approved :: MIT License
Classifier: Development Status :: 4 - Beta
Classifier: Operating System :: MacOS :: MacOS X
Classifier: Operating System :: Unix
Classifier: Intended Audience :: Science/Research
Classifier: Topic :: Scientific/Engineering :: Bio-Informatics
